rocket/__intit__.py
rocket/rocket.py
hamoudatheg_rocket-1.0.0.dist-info/METADATA
hamoudatheg_rocket-1.0.0.dist-info/WHEEL
hamoudatheg_rocket-1.0.0.dist-info/top_level.txt
hamoudatheg_rocket-1.0.0.dist-info/RECORD
