Metadata-Version: 2.1
Name: hamoudatheg-rocket
Version: 1.0.0
Summary: An awesome package that does something
Home-page: http://pypi.python.org/pypi/rocket/
Author: Hamouda
Author-email: m.guechaoui@esi-sba.dz
License: LICENSE.txt
Requires-Dist: rocket
